comobj2py/__init__.py
comobj2py/com_interface.py
comobj2py-0.1.1.dist-info/METADATA
comobj2py-0.1.1.dist-info/WHEEL
comobj2py-0.1.1.dist-info/entry_points.txt
comobj2py-0.1.1.dist-info/RECORD
