Metadata-Version: 2.4
Name: comobj2py
Version: 0.1.1
Summary: com对象转py调用源码
Author-email: haogaoxing <jjx000@qq.com>
Requires-Python: >=3.8
Requires-Dist: pywin32>=38
